{"cameraMode":{"drawMode":0,"name":"Shaded","section":"Shading Mode"},"sceneLighting":true,"audioPlay":false,"sceneViewState":{"m_AlwaysRefresh":false,"showFog":true,"showSkybox":true,"showFlares":true,"showImageEffects":true,"showParticleSystems":true,"showVisualEffectGraphs":true,"m_FxEnabled":true},"in2DMode":false,"pivot":{"x":554.0955810546875,"y":296.1875,"z":-13.640029907226563},"rotation":{"x":0.00718853622674942,"y":0.021595358848571779,"z":0.0001554242189740762,"w":-0.9997414350509644},"size":372.91986083984377,"orthographic":true}